lidarToGeo/__init__.py
lidarToGeo/ept_info.py
lidarToGeo/get_data.py
lidarToGeo/load_data.py
lidarToGeo/logger.py
lidarToGeo/schema.py
lidarToGeo-1.0.1.dist-info/LICENSE
lidarToGeo-1.0.1.dist-info/METADATA
lidarToGeo-1.0.1.dist-info/WHEEL
lidarToGeo-1.0.1.dist-info/top_level.txt
lidarToGeo-1.0.1.dist-info/RECORD
