Metadata-Version: 2.1
Name: lidarToGeo
Version: 1.0.1
Summary: A package that get lidar data from an s3 bucket and converts it to Geo raster
Home-page: https://github.com/Jabor047/LidarToGeo
Author: Jabor047
License: UNKNOWN
Platform: UNKNOWN
Classifier: Development Status :: 2 - Pre-Alpha
Classifier: Intended Audience :: Developers
Classifier: Natural Language :: English
Classifier: Programming Language :: Python :: 3
Classifier: Programming Language :: Python :: 3.6
Classifier: Programming Language :: Python :: 3.7
Classifier: Programming Language :: Python :: 3.8
Requires-Python: >=3.7
License-File: LICENSE
Requires-Dist: pandas (>=1.1.0)
Requires-Dist: numpy (>=1.19.0)
